Metadata-Version: 2.1
Name: pyrgbpalette
Version: 0.0.6
Summary: Generate rgb palette in red or rainbow
Home-page: https://github.com/myplaceit/pyrgbpalette
Author: Wolfgang Hoellinger
Author-email: wolfgang.hoellinger@myplace.eu
License: UNKNOWN
Platform: UNKNOWN
Classifier: Programming Language :: Python :: 3
Classifier: Programming Language :: Python :: 3.6
Classifier: Programming Language :: Python :: 3.7
Classifier: License :: OSI Approved :: GNU General Public License v3 or later (GPLv3+)
Classifier: Operating System :: OS Independent
Provides-Extra: dev
